{
  "msg" : "",
  "code" : 200,
  "data" : [
    {
      "appname" : "ddg",
      "appid" : 1,
      "premission" : 1,
      "admin_uid" : "28",
      "user_uid" : "",
      "guest_uid" : "25",
      "reports" : [
        {
          "id" : 23,
          "report_name" : "report1"
        },
        {
          "id" : 45,
          "report_name" : "hgjfg"
        },
        {
          "id" : 76,
          "report_name" : "report3"
        },
        {
          "id" : 88,
          "report_name" : "cddgs"
        }
      ]
    },
    {
      "appname" : "pig",
      "appid" : 15,
      "premission" : 3,
      "admin_uid" : "28",
      "user_uid" : "",
      "guest_uid" : "25",
      "reports" : [
        {
          "id" : 23,
          "report_name" : "nrd"
        },
        {
          "id" : 45,
          "report_name" : "awzx"
        },
        {
          "id" : 76,
          "report_name" : "sewd"
        },
        {
          "id" : 33,
          "report_name" : "nk"
        }
      ]
    },
    {
      "appname" : "cu",
      "appid" : 28,
      "premission" : 2,
      "admin_uid" : "28",
      "user_uid" : "",
      "guest_uid" : "25",
      "reports" : [
        {
          "id" : 45,
          "report_name" : "nrd"
        },
        {
          "id" : 27,
          "report_name" : "awzx"
        },
        {
          "id" : 34,
          "report_name" : "sewd"
        },
        {
          "id" : 64,
          "report_name" : "nk"
        }
      ]
    }
  ]
}